Metadata-Version: 2.1
Name: hdsr_wis_config_reader
Version: 1.35
Summary: Read HDSR FEWS WIS config into python objects
Home-page: https://github.com/hdsr-mid/hdsr_wis_config_reader
Author: Renier Kramer
Author-email: renier.kramer@hdsr.nl
Maintainer: Roger de Crook
Maintainer-email: roger.de.crook@hdsr.nl
License: MIT
Keywords: HDSR,FEWS,WIS,config,hdsr_wis_config_reader
Classifier: Development Status :: 5 - Production/Stable
Classifier: Intended Audience :: Developers
Classifier: Topic :: Software Development :: Build Tools
Classifier: License :: OSI Approved :: MIT License
Classifier: Programming Language :: Python :: 3.7
Classifier: Programming Language :: Python :: 3.8
Classifier: Programming Language :: Python :: 3.9
Classifier: Programming Language :: Python :: 3.10
Classifier: Programming Language :: Python :: 3.11
Classifier: Programming Language :: Python :: 3.12
Requires-Python: >=3.7
License-File: LICENSE
Requires-Dist: geopandas
Requires-Dist: lxml
Requires-Dist: hdsr-pygithub
Provides-Extra: test
Requires-Dist: pytest; extra == "test"
